Metadata-Version: 1.2
Name: travislint
Version: 1.1
Summary: An application to simplify linting of travis-ci config files.
Home-page: https://github.com/papadeltasierrra/travislint
Author: Paul D.Smith
Author-email: paul@pauldsmith.org.uk
License: UNKNOWN
Platform: UNKNOWN
Requires-Python: >=2.7, <4
